heatrapy/__init__.py
heatrapy/database/Al/cp0.txt
heatrapy/database/Al/cpa.txt
heatrapy/database/Al/k0.txt
heatrapy/database/Al/ka.txt
heatrapy/database/Al/lheat0.txt
heatrapy/database/Al/lheata.txt
heatrapy/database/Al/rho0.txt
heatrapy/database/Al/rhoa.txt
heatrapy/database/Al/tadd.txt
heatrapy/database/Al/tadi.txt
heatrapy/database/Cu/cp0.txt
heatrapy/database/Cu/cpa.txt
heatrapy/database/Cu/k0.txt
heatrapy/database/Cu/ka.txt
heatrapy/database/Cu/lheat.txt
heatrapy/database/Cu/lheat0.txt
heatrapy/database/Cu/lheata.txt
heatrapy/database/Cu/rho0.txt
heatrapy/database/Cu/rhoa.txt
heatrapy/database/Cu/tadd.txt
heatrapy/database/Cu/tadi.txt
heatrapy/database/Gd_mag/cp0.txt
heatrapy/database/Gd_mag/cpa.txt
heatrapy/database/Gd_mag/k0.txt
heatrapy/database/Gd_mag/ka.txt
heatrapy/database/Gd_mag/lheat.txt
heatrapy/database/Gd_mag/lheat0.txt
heatrapy/database/Gd_mag/lheata.txt
heatrapy/database/Gd_mag/rho0.txt
heatrapy/database/Gd_mag/rhoa.txt
heatrapy/database/Gd_mag/tadd.txt
heatrapy/database/Gd_mag/tadi.txt
heatrapy/database/MnFePSi_mag/cp0.txt
heatrapy/database/MnFePSi_mag/cpa.txt
heatrapy/database/MnFePSi_mag/k0.txt
heatrapy/database/MnFePSi_mag/ka.txt
heatrapy/database/MnFePSi_mag/lheat0.txt
heatrapy/database/MnFePSi_mag/lheata.txt
heatrapy/database/MnFePSi_mag/rho0.txt
heatrapy/database/MnFePSi_mag/rhoa.txt
heatrapy/database/MnFePSi_mag/tadd.txt
heatrapy/database/MnFePSi_mag/tadi.txt
heatrapy/database/Si/cp0.txt
heatrapy/database/Si/cpa.txt
heatrapy/database/Si/k0.txt
heatrapy/database/Si/ka.txt
heatrapy/database/Si/lheat0.txt
heatrapy/database/Si/lheata.txt
heatrapy/database/Si/rho0.txt
heatrapy/database/Si/rhoa.txt
heatrapy/database/Si/tadd.txt
heatrapy/database/Si/tadi.txt
heatrapy/database/vacuum/cp0.txt
heatrapy/database/vacuum/cpa.txt
heatrapy/database/vacuum/k0.txt
heatrapy/database/vacuum/ka.txt
heatrapy/database/vacuum/lheat0.txt
heatrapy/database/vacuum/lheata.txt
heatrapy/database/vacuum/rho0.txt
heatrapy/database/vacuum/rhoa.txt
heatrapy-2.0.11.dist-info/LICENSE
heatrapy-2.0.11.dist-info/METADATA
heatrapy-2.0.11.dist-info/WHEEL
heatrapy-2.0.11.dist-info/top_level.txt
heatrapy-2.0.11.dist-info/RECORD
