Metadata-Version: 2.1
Name: heatrapy
Version: 2.0.11
Summary: Library for simulating 1D and 2D heat transfer processes
Home-page: https://github.com/djsilva99/heatrapy
Author: Daniel Silva
Author-email: djsilva@gmx.com
License: MIT
Classifier: Development Status :: 3 - Alpha
Classifier: License :: OSI Approved :: MIT License
Classifier: Programming Language :: Python :: 3.7
Classifier: Topic :: Scientific/Engineering :: Physics
License-File: LICENSE
Requires-Dist: numpy>=1.20.1
Requires-Dist: matplotlib==3.3.4
